tableau_migration/__init__.py
tableau_migration/migration.py
tableau_migration/migration_api_rest.py
tableau_migration/migration_api_rest_models.py
tableau_migration/migration_api_rest_models_types.py
tableau_migration/migration_content.py
tableau_migration/migration_content_permissions.py
tableau_migration/migration_content_schedules.py
tableau_migration/migration_content_schedules_cloud.py
tableau_migration/migration_content_schedules_server.py
tableau_migration/migration_content_search.py
tableau_migration/migration_engine.py
tableau_migration/migration_engine_actions.py
tableau_migration/migration_engine_endpoints_search.py
tableau_migration/migration_engine_hooks.py
tableau_migration/migration_engine_hooks_filters.py
tableau_migration/migration_engine_hooks_filters_interop.py
tableau_migration/migration_engine_hooks_initializemigration.py
tableau_migration/migration_engine_hooks_interop.py
tableau_migration/migration_engine_hooks_mappings.py
tableau_migration/migration_engine_hooks_mappings_interop.py
tableau_migration/migration_engine_hooks_postpublish.py
tableau_migration/migration_engine_hooks_postpublish_interop.py
tableau_migration/migration_engine_hooks_transformers.py
tableau_migration/migration_engine_hooks_transformers_interop.py
tableau_migration/migration_engine_manifest.py
tableau_migration/migration_engine_migrators.py
tableau_migration/migration_engine_migrators_batch.py
tableau_migration/migration_engine_options.py
tableau_migration/migration_engine_pipelines.py
tableau_migration/migration_enum.py
tableau_migration/migration_logger.py
tableau_migration/migration_services.py
tableau_migration/bin/Microsoft.Extensions.AmbientMetadata.Application.dll
tableau_migration/bin/Microsoft.Extensions.Caching.Abstractions.dll
tableau_migration/bin/Microsoft.Extensions.Caching.Memory.dll
tableau_migration/bin/Microsoft.Extensions.Compliance.Abstractions.dll
tableau_migration/bin/Microsoft.Extensions.Configuration.Abstractions.dll
tableau_migration-5.3.1.dist-info/METADATA
tableau_migration-5.3.1.dist-info/WHEEL
tableau_migration-5.3.1.dist-info/licenses/LICENSE
tableau_migration-5.3.1.dist-info/RECORD
